PythonXuexiYuanFix1/README.md
PythonXuexiYuanFix1/__init__.py
PythonXuexiYuanFix1/__main__.py
PythonXuexiYuanFix1/file.epub
PythonXuexiYuanFix1/index.html
PythonXuexiYuanFix1/css/__init__.py
PythonXuexiYuanFix1/css/annotations.css
PythonXuexiYuanFix1/css/main.css
PythonXuexiYuanFix1/css/normalize.css
PythonXuexiYuanFix1/css/popup.css
PythonXuexiYuanFix1/font/__init__.py
PythonXuexiYuanFix1/font/fontello.eot
PythonXuexiYuanFix1/font/fontello.svg
PythonXuexiYuanFix1/font/fontello.ttf
PythonXuexiYuanFix1/font/fontello.woff
PythonXuexiYuanFix1/img/__init__.py
PythonXuexiYuanFix1/img/annotator-glyph-sprite.png
PythonXuexiYuanFix1/img/annotator-icon-sprite.png
PythonXuexiYuanFix1/img/apple-touch-icon.png
PythonXuexiYuanFix1/img/cancelfullscreen.png
PythonXuexiYuanFix1/img/close.png
PythonXuexiYuanFix1/img/fullscreen.png
PythonXuexiYuanFix1/img/loader.gif
PythonXuexiYuanFix1/img/menu-icon.png
PythonXuexiYuanFix1/img/save.png
PythonXuexiYuanFix1/img/saved.png
PythonXuexiYuanFix1/img/settings-s.png
PythonXuexiYuanFix1/img/settings.png
PythonXuexiYuanFix1/img/star.png
PythonXuexiYuanFix1/js/__init__.py
PythonXuexiYuanFix1/js/epub.js
PythonXuexiYuanFix1/js/epub.min.js
PythonXuexiYuanFix1/js/epub.min.map
PythonXuexiYuanFix1/js/hooks.min.js
PythonXuexiYuanFix1/js/hooks.min.map
PythonXuexiYuanFix1/js/reader.js
PythonXuexiYuanFix1/js/reader.js.map
PythonXuexiYuanFix1/js/reader.min.js
PythonXuexiYuanFix1/js/reader.min.map
PythonXuexiYuanFix1/js/hooks/__init__.py
PythonXuexiYuanFix1/js/hooks/extensions/__init__.py
PythonXuexiYuanFix1/js/hooks/extensions/highlight.js
PythonXuexiYuanFix1/js/libs/__init__.py
PythonXuexiYuanFix1/js/libs/jquery.min.js
PythonXuexiYuanFix1/js/libs/localforage.min.js
PythonXuexiYuanFix1/js/libs/screenfull.js
PythonXuexiYuanFix1/js/libs/screenfull.min.js
PythonXuexiYuanFix1/js/libs/zip.min.js
PythonXuexiYuanFix1/js/plugins/__init__.py
PythonXuexiYuanFix1/js/plugins/hypothesis.js
PythonXuexiYuanFix1/js/plugins/search.js
python_xuexi_yuan_fix1-2025.3.24.1.dist-info/METADATA
python_xuexi_yuan_fix1-2025.3.24.1.dist-info/WHEEL
python_xuexi_yuan_fix1-2025.3.24.1.dist-info/entry_points.txt
python_xuexi_yuan_fix1-2025.3.24.1.dist-info/top_level.txt
python_xuexi_yuan_fix1-2025.3.24.1.dist-info/RECORD
